odoo/addons/web_pivot_computed_measure/README.rst
odoo/addons/web_pivot_computed_measure/__init__.py
odoo/addons/web_pivot_computed_measure/__manifest__.py
odoo/addons/web_pivot_computed_measure/demo/demo_users_pivot_view.xml
odoo/addons/web_pivot_computed_measure/i18n/ca.po
odoo/addons/web_pivot_computed_measure/i18n/es.po
odoo/addons/web_pivot_computed_measure/i18n/it.po
odoo/addons/web_pivot_computed_measure/i18n/tr.po
odoo/addons/web_pivot_computed_measure/i18n/web_pivot_computed_measure.pot
odoo/addons/web_pivot_computed_measure/readme/CONTRIBUTORS.md
odoo/addons/web_pivot_computed_measure/readme/DESCRIPTION.md
odoo/addons/web_pivot_computed_measure/readme/ROADMAP.md
odoo/addons/web_pivot_computed_measure/readme/USAGE.md
odoo/addons/web_pivot_computed_measure/static/description/icon.png
odoo/addons/web_pivot_computed_measure/static/description/index.html
odoo/addons/web_pivot_computed_measure/static/src/dropdown_item_custom_measure/dropdown_item_custom_measure.esm.js
odoo/addons/web_pivot_computed_measure/static/src/dropdown_item_custom_measure/dropdown_item_custom_measure.scss
odoo/addons/web_pivot_computed_measure/static/src/dropdown_item_custom_measure/dropdown_item_custom_measure.xml
odoo/addons/web_pivot_computed_measure/static/src/helpers/utils.esm.js
odoo/addons/web_pivot_computed_measure/static/src/pivot/pivot_controller.esm.js
odoo/addons/web_pivot_computed_measure/static/src/pivot/pivot_model.esm.js
odoo/addons/web_pivot_computed_measure/static/src/pivot/pivot_renderer.esm.js
odoo/addons/web_pivot_computed_measure/static/src/pivot/pivot_view.xml
odoo/addons/web_pivot_computed_measure/static/src/report_view_measures/report_view_measures.esm.js
odoo/addons/web_pivot_computed_measure/static/src/report_view_measures/report_view_measures.xml
odoo/addons/web_pivot_computed_measure/static/src/test/test.esm.js
odoo/addons/web_pivot_computed_measure/tests/__init__.py
odoo/addons/web_pivot_computed_measure/tests/test_ui_pivot.py
odoo_addon_web_pivot_computed_measure-18.0.1.0.5.1.dist-info/METADATA
odoo_addon_web_pivot_computed_measure-18.0.1.0.5.1.dist-info/WHEEL
odoo_addon_web_pivot_computed_measure-18.0.1.0.5.1.dist-info/top_level.txt
odoo_addon_web_pivot_computed_measure-18.0.1.0.5.1.dist-info/RECORD
